{
  "id": "mizukage-1-byakuren",
  "name": "Byakuren — 1er Mizukage",
  "category": "kage",
  "era": [
    "naruto-backstory"
  ],
  "tags": [
    "kage",
    "mizukage",
    "kiri",
    "fondateur",
    "eau",
    "brume",
    "kirigakure"
  ],
  "summary": "Premier Mizukage, fondateur de Kirigakure et père de la nation de l'Eau",
  "details": [
    "Fondateur de Kirigakure, le village caché de la Brume, établi sur les îles du Pays de l'Eau",
    "A établi les premières traditions des chasseurs de démons, des guerriers spécialisés dans la traque des traîtres",
    "Connu pour ses techniques d'eau dévastatrices adaptées à l'environnement marin de Kiri",
    "A participé à la première réunion des cinq Kage où les bijū furent distribués entre les nations",
    "Les archives sur son règne sont rares, mais il posa les fondations de la puissance maritime de Kiri"
  ]
}
